selenium-stubs/METADATA.toml
selenium-stubs/__init__.pyi
selenium-stubs/common/__init__.pyi
selenium-stubs/common/exceptions.pyi
selenium-stubs/webdriver/__init__.pyi
selenium-stubs/webdriver/android/__init__.pyi
selenium-stubs/webdriver/android/webdriver.pyi
selenium-stubs/webdriver/blackberry/__init__.pyi
selenium-stubs/webdriver/blackberry/webdriver.pyi
selenium-stubs/webdriver/chrome/__init__.pyi
selenium-stubs/webdriver/chrome/options.pyi
selenium-stubs/webdriver/chrome/remote_connection.pyi
selenium-stubs/webdriver/chrome/service.pyi
selenium-stubs/webdriver/chrome/webdriver.pyi
selenium-stubs/webdriver/common/__init__.pyi
selenium-stubs/webdriver/common/action_chains.pyi
selenium-stubs/webdriver/common/alert.pyi
selenium-stubs/webdriver/common/by.pyi
selenium-stubs/webdriver/common/desired_capabilities.pyi
selenium-stubs/webdriver/common/keys.pyi
selenium-stubs/webdriver/common/proxy.pyi
selenium-stubs/webdriver/common/service.pyi
selenium-stubs/webdriver/common/touch_actions.pyi
selenium-stubs/webdriver/common/utils.pyi
selenium-stubs/webdriver/common/actions/__init__.pyi
selenium-stubs/webdriver/common/actions/action_builder.pyi
selenium-stubs/webdriver/common/actions/input_device.pyi
selenium-stubs/webdriver/common/actions/interaction.pyi
selenium-stubs/webdriver/common/actions/key_actions.pyi
selenium-stubs/webdriver/common/actions/key_input.pyi
selenium-stubs/webdriver/common/actions/mouse_button.pyi
selenium-stubs/webdriver/common/actions/pointer_actions.pyi
selenium-stubs/webdriver/common/actions/pointer_input.pyi
selenium-stubs/webdriver/common/html5/__init__.pyi
selenium-stubs/webdriver/common/html5/application_cache.pyi
selenium-stubs/webdriver/edge/__init__.pyi
selenium-stubs/webdriver/edge/options.pyi
selenium-stubs/webdriver/edge/service.pyi
selenium-stubs/webdriver/edge/webdriver.pyi
selenium-stubs/webdriver/firefox/__init__.pyi
selenium-stubs/webdriver/firefox/extension_connection.pyi
selenium-stubs/webdriver/firefox/firefox_binary.pyi
types_selenium-3.141.8.dist-info/METADATA
types_selenium-3.141.8.dist-info/WHEEL
types_selenium-3.141.8.dist-info/top_level.txt
types_selenium-3.141.8.dist-info/RECORD
